psireact/__init__.py
psireact/lba.py
psireact/model.py
psireact/plot.py
psireact-0.2.15.dist-info/LICENSE
psireact-0.2.15.dist-info/METADATA
psireact-0.2.15.dist-info/WHEEL
psireact-0.2.15.dist-info/top_level.txt
psireact-0.2.15.dist-info/RECORD
