Metadata-Version: 2.1
Name: psireact
Version: 0.2.15
Summary: Response time modeling of psychology experiments
Home-page: https://github.com/mortonne/psireact
Author: Neal Morton
Author-email: mortonne@gmail.com
License: UNKNOWN
Platform: UNKNOWN
Classifier: Programming Language :: Python :: 3
Classifier: License :: OSI Approved :: GNU Lesser General Public License v3 or later (LGPLv3+)
Classifier: Operating System :: OS Independent
Requires-Dist: numpy
Requires-Dist: scipy
Requires-Dist: pandas
Requires-Dist: seaborn
Requires-Dist: pymc3
